flask_scheduler/__init__.py
flask_scheduler/scheduler.py
Flask_Scheduler-0.0.51.dist-info/LICENSE
Flask_Scheduler-0.0.51.dist-info/METADATA
Flask_Scheduler-0.0.51.dist-info/WHEEL
Flask_Scheduler-0.0.51.dist-info/top_level.txt
Flask_Scheduler-0.0.51.dist-info/RECORD
